{
 "game": "Indiana Fever (Women) v Toronto Tempo (Women)",
 "groups": [
  {
   "TG": "",
   "codes": {}
  },
  {
   "TG": "",
   "codes": {}
  },
  {
   "TG": "",
   "codes": {}
  },
  {
   "TG": "",
   "codes": {}
  },
  {
   "TG": "",
   "codes": {}
  },
  {
   "TG": "",
   "codes": {}
  },
  {
   "TG": "Fouls",
   "codes": {}
  },
  {
   "TG": "Free Throws Scored",
   "codes": {}
  },
  {
   "TG": "Two-Point Field Goals Scored",
   "codes": {}
  },
  {
   "TG": "Three-Point Field Goals Scored",
   "codes": {}
  },
  {
   "TG": "Rebounds",
   "codes": {}
  },
  {
   "TG": "Assists",
   "codes": {}
  },
  {
   "TG": "Players' stats",
   "codes": {
    "1807": "Brittney Sykes line=19.5",
    "1806": "Brittney Sykes line=19.5",
    "4649": "Kelsey Mitchell line=10",
    "1495": "Kelsey Mitchell line=2.5",
    "1496": "Kelsey Mitchell line=2.5",
    "15979": "Kelsey Mitchell line=1",
    "5671": "Kelsey Mitchell line=21.5",
    "5672": "Kelsey Mitchell line=21.5",
    "5673": "Kelsey Mitchell line=22.5",
    "5674": "Kelsey Mitchell line=22.5",
    "7141": "Kelsey Mitchell line=4.5",
    "7142": "Kelsey Mitchell line=4.5",
    "1489": "Kelsey Mitchell line=2.5",
    "1490": "Kelsey Mitchell line=2.5",
    "1491": "Kelsey Mitchell line=2.5",
    "1492": "Kelsey Mitchell line=2.5",
    "3096": "Kelsey Mitchell/Marina Mabrey line=-1.5",
    "3097": "Kelsey Mitchell/Marina Mabrey line=1.5",
    "3450": "Caitlin Clark/Aliyah Boston line=35.5",
    "3451": "Caitlin Clark/Aliyah Boston line=35.5",
    "16413": "Brittney Sykes line=3",
    "16414": "Caitlin Clark line=3",
    "16427": "Isabelle Harrison line=17.5",
    "16428": "Isabelle Harrison line=17.5"
   }
  },
  {
   "TG": "Players' stats",
   "codes": {
    "1807": "Kelsey Mitchell line=5.5",
    "1806": "Kelsey Mitchell line=5.5"
   }
  }
 ]
}